gharbala/main.py
gharbala/post_template.jinja.html
gharbala/update_old_post_with_playlist.py
gharbala-0.1.9.dist-info/entry_points.txt
gharbala-0.1.9.dist-info/WHEEL
gharbala-0.1.9.dist-info/METADATA
gharbala-0.1.9.dist-info/RECORD
